unirate/__init__.py
unirate/client.py
unirate/exceptions.py
unirate_api-1.0.0.dist-info/METADATA
unirate_api-1.0.0.dist-info/WHEEL
unirate_api-1.0.0.dist-info/top_level.txt
unirate_api-1.0.0.dist-info/RECORD
